rest_scaffold/__init__.py
rest_scaffold/apps.py
rest_scaffold/middleware.py
rest_scaffold/settings.py
rest_scaffold/tests.py
rest_scaffold/urls.py
rest_scaffold/views.py
rest_scaffold/templatetags/__init__.py
rest_scaffold/templatetags/rest_scaffold.py
django_rest_scaffold-0.1.0.dist-info/LICENSE
django_rest_scaffold-0.1.0.dist-info/METADATA
django_rest_scaffold-0.1.0.dist-info/WHEEL
django_rest_scaffold-0.1.0.dist-info/top_level.txt
django_rest_scaffold-0.1.0.dist-info/RECORD
