Metadata-Version: 2.1
Name: django-rest-scaffold
Version: 0.1.0
Summary: A re-useable Django helper app for integrating rest-scaffold.js.
Home-page: https://github.com/gregschmit/django-rest-scaffold
Author: Gregory N. Schmit
Author-email: me@gregschmit.com
License: MIT
Platform: UNKNOWN
Classifier: Environment :: Web Environment
Classifier: Framework :: Django
Classifier: Intended Audience :: Developers
Classifier: License :: OSI Approved :: MIT License
Classifier: Programming Language :: Python :: 3
Requires-Dist: Django (>=2)
Requires-Dist: djangorestframework (>=3)
